{
  "split": "train",
  "trial_id": 101,
  "skipped": 0,
  "mask_file": "apple3.png",
  "image_size": "512x512",
  "target_max_dim": 393,
  "rotation_deg": 44.56292889479121,
  "dx": -1,
  "dy": 9,
  "obj_munsell": "5YR 3/4",
  "order": "B_first",
  "correct_label": 0,
  "resample_attempts_total": 3,
  "resample_attempts_tint": 1,
  "resample_attempts_object": 3,
  "initial_path": "train/trial_000101/initial.png",
  "cand1_path": "train/trial_000101/cand1.png",
  "cand2_path": "train/trial_000101/cand2.png",
  "tint_lab": "[80.0, -10.0, 0.0]",
  "bg_lab_pre": "[60.0, 0.0, 0.0]",
  "obj_lab_pre": "[30.37867, 14.82182, 17.71088]",
  "obj_lab_post_init": "[29.45403, 8.3017, 16.2813]",
  "bg_lab_post_init": "[60.00106, -7.91781, 0.00094]",
  "obj_rgb_pre": "[101, 62, 45]",
  "bg_rgb_pre": "[145, 145, 145]",
  "tint_rgb": "[178, 204, 198]",
  "obj_rgb_post_init": "[90, 64, 45]",
  "bg_rgb_post_init": "[129, 149, 144]",
  "candA_obj_rgb": "[101, 62, 45]",
  "candB_obj_rgb": "[90, 64, 45]",
  "cand_bg_rgb": "[145, 145, 145]",
  "geometry": {
    "S_max": 393,
    "angle": 44.56292889479121,
    "dx": -1,
    "dy": 9
  }
}