{
  "split": "train",
  "trial_id": 75,
  "skipped": 0,
  "mask_file": "apple2.png",
  "image_size": "512x512",
  "target_max_dim": 446,
  "rotation_deg": -1.0780304706098391,
  "dx": -7,
  "dy": 11,
  "obj_munsell": "5B 6/8",
  "order": "B_first",
  "correct_label": 0,
  "resample_attempts_total": 1,
  "resample_attempts_tint": 1,
  "resample_attempts_object": 1,
  "initial_path": "train/trial_000075/initial.png",
  "cand1_path": "train/trial_000075/cand1.png",
  "cand2_path": "train/trial_000075/cand2.png",
  "tint_lab": "[80.0, 0.0, 15.0]",
  "bg_lab_pre": "[60.0, 0.0, 0.0]",
  "obj_lab_pre": "[61.0465, -19.53399, -29.90713]",
  "obj_lab_post_init": "[59.76903, -28.31578, -16.17876]",
  "bg_lab_post_init": "[60.00113, -0.00181, 11.87592]",
  "obj_rgb_pre": "[24, 159, 199]",
  "bg_rgb_pre": "[145, 145, 145]",
  "tint_rgb": "[210, 197, 171]",
  "obj_rgb_post_init": "[27, 159, 171]",
  "bg_rgb_post_init": "[153, 144, 124]",
  "candA_obj_rgb": "[24, 159, 199]",
  "candB_obj_rgb": "[27, 159, 171]",
  "cand_bg_rgb": "[145, 145, 145]",
  "geometry": {
    "S_max": 446,
    "angle": -1.0780304706098391,
    "dx": -7,
    "dy": 11
  }
}